gg/__init__.py
gg/branch.py
gg/commit.py
gg/confirm.py
gg/exception.py
gg/log.py
gg/ls.py
gg/main.py
gg/repo.py
gg/restack.py
gg/tree.py
git_squared-0.1a1.dist-info/METADATA
git_squared-0.1a1.dist-info/WHEEL
git_squared-0.1a1.dist-info/entry_points.txt
git_squared-0.1a1.dist-info/top_level.txt
git_squared-0.1a1.dist-info/RECORD
