Metadata-Version: 2.2
Name: git-squared
Version: 0.1a1
Summary: Add your description here
Author-email: Andrew Peters <apete343@gmail.com>
Requires-Python: >=3.9
Requires-Dist: arguably>=1.3.0
Requires-Dist: gitpython>=3.1.44
Requires-Dist: questionary>=2.1.0
Requires-Dist: rich>=13.9.4
